powerbpy/__init__.py
powerbpy/background_image.py
powerbpy/button.py
powerbpy/card.py
powerbpy/chart.py
powerbpy/dashboard.py
powerbpy/data_set.py
powerbpy/dataset_csv.py
powerbpy/dataset_tmdl.py
powerbpy/page.py
powerbpy/sanky_chart.py
powerbpy/shape_map.py
powerbpy/slicer.py
powerbpy/table.py
powerbpy/text_box.py
powerbpy/visual.py
powerbpy/common/layout_utils.py
powerbpy/dashboard_resources/.gitignore
powerbpy/dashboard_resources/blank_template.pbip
powerbpy/dashboard_resources/blank_template.Report/.platform
powerbpy/dashboard_resources/blank_template.Report/definition.pbir
powerbpy/dashboard_resources/blank_template.Report/StaticResources/SharedResources/BaseThemes/CY24SU10.json
powerbpy/dashboard_resources/blank_template.Report/definition/report.json
powerbpy/dashboard_resources/blank_template.Report/definition/version.json
powerbpy/dashboard_resources/blank_template.Report/definition/pages/pages.json
powerbpy/dashboard_resources/blank_template.Report/definition/pages/915e09e5204515bccac2/page.json
powerbpy/dashboard_resources/blank_template.SemanticModel/.platform
powerbpy/dashboard_resources/blank_template.SemanticModel/definition.pbism
powerbpy/dashboard_resources/blank_template.SemanticModel/diagramLayout.json
powerbpy/dashboard_resources/blank_template.SemanticModel/.pbi/editorSettings.json
powerbpy/dashboard_resources/blank_template.SemanticModel/definition/database.tmdl
powerbpy/dashboard_resources/blank_template.SemanticModel/definition/model.tmdl
powerbpy/dashboard_resources/blank_template.SemanticModel/definition/cultures/en-US.tmdl
powerbpy/dashboard_resources/python_resources/DateTable.tmdl
powerbpy/dashboard_resources/python_resources/LocalDateTable_FILE_ID.tmdl
powerbpy-0.2.0.dist-info/METADATA
powerbpy-0.2.0.dist-info/WHEEL
powerbpy-0.2.0.dist-info/licenses/LICENSE
powerbpy-0.2.0.dist-info/RECORD
