Metadata-Version: 2.4
Name: powerbpy
Version: 0.2.0
Summary: Create Power BI dashboards using python
Project-URL: Homepage, https://github.com/Russell-Shean/powerbpy
Project-URL: Issues, https://github.com/Russell-Shean/powerbpy/issues
Author-email: Russell Shean <russshean@gmail.com>
License-Expression: GPL-3.0-or-later
License-File: LICENSE
Classifier: Operating System :: OS Independent
Classifier: Programming Language :: Python :: 3
Requires-Python: >=3.10
Requires-Dist: azure-identity
Requires-Dist: azure-storage-blob
Requires-Dist: azure-storage-file-datalake
Requires-Dist: keyring
Requires-Dist: pandas
